<problem display_name="H19">
  <multiplechoiceresponse>
    <label>Who is the Project Manager?
A. The one is assigned to lead the project
B. The one is accountable for accomplishing the specific goal of the project within prior agreed time and budget constraints</label>
    <choicegroup>
      <choice correct="false">A</choice>
      <choice correct="false">B</choice>
      <choice correct="true">A and B</choice>
      <choice correct="false">A or B</choice>
      <choice correct="false">neither A nor B</choice>
    </choicegroup>
  </multiplechoiceresponse>
</problem>