<problem display_name="M55">
  <multiplechoiceresponse>
    <label>Complex human endeavors involve planning on two levels, and answering the questions such as "how do we do it?, When, What resources should we append" is on ______ level</label>
    <choicegroup>
      <choice correct="false">Strategic</choice>
      <choice correct="true">Tactical</choice>
      <choice correct="false">Hard</choice>
      <choice correct="false">Easy</choice>
    </choicegroup>
  </multiplechoiceresponse>
</problem>